odoo/addons/ssi_bill_of_service_project/README.rst
odoo/addons/ssi_bill_of_service_project/__init__.py
odoo/addons/ssi_bill_of_service_project/__manifest__.py
odoo/addons/ssi_bill_of_service_project/models/__init__.py
odoo/addons/ssi_bill_of_service_project/models/bill_of_service.py
odoo/addons/ssi_bill_of_service_project/models/bill_of_service_pricelist.py
odoo/addons/ssi_bill_of_service_project/models/bill_of_service_pricelist_task.py
odoo/addons/ssi_bill_of_service_project/models/bill_of_service_work_task.py
odoo/addons/ssi_bill_of_service_project/security/ir.model.access.csv
odoo/addons/ssi_bill_of_service_project/static/description/icon.png
odoo/addons/ssi_bill_of_service_project/views/bill_of_service_pricelist_views.xml
odoo/addons/ssi_bill_of_service_project/views/bill_of_service_views.xml
odoo14_addon_ssi_bill_of_service_project-14.0.2.2.4.dev1.dist-info/METADATA
odoo14_addon_ssi_bill_of_service_project-14.0.2.2.4.dev1.dist-info/WHEEL
odoo14_addon_ssi_bill_of_service_project-14.0.2.2.4.dev1.dist-info/top_level.txt
odoo14_addon_ssi_bill_of_service_project-14.0.2.2.4.dev1.dist-info/RECORD
