Metadata-Version: 2.1
Name: odoo14-addon-ssi-bill-of-service-project
Version: 14.0.2.2.4.dev1
Summary: Bill of Service - Project Integration
Home-page: https://simetri-sinergi.id
Author: PT. Simetri Sinergi Indonesia, OpenSynergy Indonesia
License: AGPL-3
Platform: UNKNOWN
Classifier: Programming Language :: Python
Classifier: Framework :: Odoo
Classifier: Framework :: Odoo :: 14.0
Classifier: License :: OSI Approved :: GNU Affero General Public License v3
Requires-Python: >=3.6
Requires-Dist: odoo14-addon-ssi-bill-of-service
Requires-Dist: odoo14-addon-ssi-task-work-log
Requires-Dist: odoo14-addon-ssi-work-log-cost
Requires-Dist: odoo <14.1dev,>=14.0a
